sat5ptools.py
sat5ptools-0.2.4.dist-info/DESCRIPTION.rst
sat5ptools-0.2.4.dist-info/METADATA
sat5ptools-0.2.4.dist-info/RECORD
sat5ptools-0.2.4.dist-info/WHEEL
sat5ptools-0.2.4.dist-info/entry_points.txt
sat5ptools-0.2.4.dist-info/metadata.json
sat5ptools-0.2.4.dist-info/top_level.txt
