Metadata-Version: 2.0
Name: sat5ptools
Version: 0.2.4
Summary: 5P Self Assessment Tools - commands to work with sat5p conversations
Home-page: https://github.com/DanielBaird/self-assessment-tool
Author: Daniel Baird
Author-email: daniel@danielbaird.com
License: Apache2
Keywords: chat 5p selfassessment conversation
Platform: UNKNOWN
Classifier: Development Status :: 3 - Alpha
Classifier: Environment :: Console
Classifier: License :: OSI Approved :: Apache Software License
Requires-Dist: Click
Requires-Dist: openpyxl
